<annotation>
	<folder>航拍数据集</folder>
	<filename>c2400.jpg</filename>
	<path>/home/hxzh02/文档/航拍数据集/c2400.jpg</path>
	<source>
		<database>Unknown</database>
	</source>
	<size>
		<width>480</width>
		<height>270</height>
		<depth>3</depth>
	</size>
	<segmented>0</segmented>
	<object>
		<name>tower_head</name>
		<pose>Unspecified</pose>
		<truncated>0</truncated>
		<difficult>0</difficult>
		<bndbox>
			<xmin>155</xmin>
			<ymin>20</ymin>
			<xmax>230</xmax>
			<ymax>57</ymax>
		</bndbox>
	</object>
	<object>
		<name>tower_foot</name>
		<pose>Unspecified</pose>
		<truncated>0</truncated>
		<difficult>0</difficult>
		<bndbox>
			<xmin>174</xmin>
			<ymin>151</ymin>
			<xmax>212</xmax>
			<ymax>188</ymax>
		</bndbox>
	</object>
	<object>
		<name>tower_body</name>
		<pose>Unspecified</pose>
		<truncated>0</truncated>
		<difficult>0</difficult>
		<bndbox>
			<xmin>153</xmin>
			<ymin>18</ymin>
			<xmax>233</xmax>
			<ymax>191</ymax>
		</bndbox>
	</object>
</annotation>
