<annotation>
	<folder>used</folder>
	<filename>c1830.jpg</filename>
	<path>/home/hxzh02/YOLOV5/yolov5_tower_rec/dataset/used/c1830.jpg</path>
	<source>
		<database>Unknown</database>
	</source>
	<size>
		<width>640</width>
		<height>360</height>
		<depth>3</depth>
	</size>
	<segmented>0</segmented>
	<object>
		<name>tower_up</name>
		<pose>Unspecified</pose>
		<truncated>0</truncated>
		<difficult>0</difficult>
		<bndbox>
			<xmin>307</xmin>
			<ymin>57</ymin>
			<xmax>522</xmax>
			<ymax>336</ymax>
		</bndbox>
	</object>
	<object>
		<name>tower_up</name>
		<pose>Unspecified</pose>
		<truncated>0</truncated>
		<difficult>0</difficult>
		<bndbox>
			<xmin>506</xmin>
			<ymin>256</ymin>
			<xmax>566</xmax>
			<ymax>338</ymax>
		</bndbox>
	</object>
</annotation>
