<annotation>
	<folder>used</folder>
	<filename>u450.jpg</filename>
	<path>/home/hxzh02/YOLOV5/yolov5_tower_rec/dataset/used/u450.jpg</path>
	<source>
		<database>Unknown</database>
	</source>
	<size>
		<width>480</width>
		<height>268</height>
		<depth>3</depth>
	</size>
	<segmented>0</segmented>
	<object>
		<name>tower_up</name>
		<pose>Unspecified</pose>
		<truncated>1</truncated>
		<difficult>0</difficult>
		<bndbox>
			<xmin>198</xmin>
			<ymin>23</ymin>
			<xmax>319</xmax>
			<ymax>268</ymax>
		</bndbox>
	</object>
</annotation>
